[
    {
        "jmhVersion" : "1.37",
        "benchmark" : "org.hestiastore.index.benchmark.storage.multithread.write.HestiaStoreCompressWriteMultiThreadBenchmark.writeThroughput",
        "mode" : "thrpt",
        "threads" : 4,
        "forks" : 1,
        "jvm" : "/opt/homebrew/Cellar/openjdk@21/21.0.10/libexec/openjdk.jdk/Contents/Home/bin/java",
        "jvmArgs" : [
            "--add-opens=java.base/java.lang=ALL-UNNAMED",
            "--add-opens=java.base/java.lang.reflect=ALL-UNNAMED",
            "--add-opens=java.base/java.io=ALL-UNNAMED",
            "--add-opens=java.base/java.nio=ALL-UNNAMED",
            "--add-opens=java.base/sun.nio.ch=ALL-UNNAMED",
            "--add-opens=jdk.compiler/com.sun.tools.javac=ALL-UNNAMED",
            "--add-opens=jdk.compiler/com.sun.tools.javac.api=ALL-UNNAMED",
            "--add-opens=jdk.compiler/com.sun.tools.javac.code=ALL-UNNAMED",
            "--add-opens=jdk.compiler/com.sun.tools.javac.comp=ALL-UNNAMED",
            "--add-opens=jdk.compiler/com.sun.tools.javac.file=ALL-UNNAMED",
            "--add-opens=jdk.compiler/com.sun.tools.javac.main=ALL-UNNAMED",
            "--add-opens=jdk.compiler/com.sun.tools.javac.model=ALL-UNNAMED",
            "--add-opens=jdk.compiler/com.sun.tools.javac.parser=ALL-UNNAMED",
            "--add-opens=jdk.compiler/com.sun.tools.javac.processing=ALL-UNNAMED",
            "--add-opens=jdk.compiler/com.sun.tools.javac.util=ALL-UNNAMED",
            "-Xmx10000m",
            "-Ddir=/Volumes/ponrava/test-index",
            "-Dengine=writeMultiThreadHestiaStoreCompress",
            "-DbenchmarkThreads=4",
            "-DbenchmarkPreloadEntryCount=10000000",
            "-DbenchmarkMissProbability=0.2"
        ],
        "jdkVersion" : "21.0.10",
        "vmName" : "OpenJDK 64-Bit Server VM",
        "vmVersion" : "21.0.10",
        "warmupIterations" : 10,
        "warmupTime" : "20 s",
        "warmupBatchSize" : 1,
        "measurementIterations" : 25,
        "measurementTime" : "20 s",
        "measurementBatchSize" : 1,
        "primaryMetric" : {
            "score" : 175413.4106614372,
            "scoreError" : 158387.15985587187,
            "scoreConfidence" : [
                17026.25080556533,
                333800.57051730907
            ],
            "scorePercentiles" : {
                "0.0" : 708.064945413452,
                "50.0" : 86778.7768162368,
                "90.0" : 638386.9913281783,
                "95.0" : 691604.4264200926,
                "99.0" : 708628.7972277844,
                "99.9" : 708628.7972277844,
                "99.99" : 708628.7972277844,
                "99.999" : 708628.7972277844,
                "99.9999" : 708628.7972277844,
                "100.0" : 708628.7972277844
            },
            "scoreUnit" : "ops/s",
            "rawData" : [
                [
                    275124.9161998119,
                    370603.23892506864,
                    237148.24794708,
                    174209.00892864564,
                    1578.5779341067068,
                    86778.7768162368,
                    708628.7972277844,
                    218058.6976055771,
                    8148.431592747975,
                    651880.8945354784,
                    31689.72844413034,
                    158757.8131951061,
                    79444.38878347044,
                    629391.0558566449,
                    49092.819781502694,
                    24511.167762106823,
                    209769.17736905973,
                    165703.78170585417,
                    230551.4958563839,
                    63585.54723035815,
                    3653.2972647081915,
                    3956.826899091976,
                    708.064945413452,
                    878.1097492601003,
                    1482.4039803014816
                ]
            ]
        },
        "secondaryMetrics" : {
        }
    }
]


