[
    {
        "jmhVersion" : "1.37",
        "benchmark" : "org.hestiastore.index.benchmark.storage.singlethread.read.HestiaStoreCompressReadSingleThreadBenchmark.readThroughput",
        "mode" : "thrpt",
        "threads" : 1,
        "forks" : 1,
        "jvm" : "/opt/homebrew/Cellar/openjdk@21/21.0.10/libexec/openjdk.jdk/Contents/Home/bin/java",
        "jvmArgs" : [
            "--add-opens=java.base/java.lang=ALL-UNNAMED",
            "--add-opens=java.base/java.lang.reflect=ALL-UNNAMED",
            "--add-opens=java.base/java.io=ALL-UNNAMED",
            "--add-opens=java.base/java.nio=ALL-UNNAMED",
            "--add-opens=java.base/sun.nio.ch=ALL-UNNAMED",
            "--add-opens=jdk.compiler/com.sun.tools.javac=ALL-UNNAMED",
            "--add-opens=jdk.compiler/com.sun.tools.javac.api=ALL-UNNAMED",
            "--add-opens=jdk.compiler/com.sun.tools.javac.code=ALL-UNNAMED",
            "--add-opens=jdk.compiler/com.sun.tools.javac.comp=ALL-UNNAMED",
            "--add-opens=jdk.compiler/com.sun.tools.javac.file=ALL-UNNAMED",
            "--add-opens=jdk.compiler/com.sun.tools.javac.main=ALL-UNNAMED",
            "--add-opens=jdk.compiler/com.sun.tools.javac.model=ALL-UNNAMED",
            "--add-opens=jdk.compiler/com.sun.tools.javac.parser=ALL-UNNAMED",
            "--add-opens=jdk.compiler/com.sun.tools.javac.processing=ALL-UNNAMED",
            "--add-opens=jdk.compiler/com.sun.tools.javac.util=ALL-UNNAMED",
            "-Xmx10000m",
            "-Ddir=/Volumes/ponrava/test-index",
            "-Dengine=readSingleThreadHestiaStoreCompress",
            "-DbenchmarkThreads=1",
            "-DbenchmarkPreloadEntryCount=10000000",
            "-DbenchmarkMissProbability=0.2"
        ],
        "jdkVersion" : "21.0.10",
        "vmName" : "OpenJDK 64-Bit Server VM",
        "vmVersion" : "21.0.10",
        "warmupIterations" : 10,
        "warmupTime" : "20 s",
        "warmupBatchSize" : 1,
        "measurementIterations" : 25,
        "measurementTime" : "20 s",
        "measurementBatchSize" : 1,
        "primaryMetric" : {
            "score" : 7739.621074640492,
            "scoreError" : 80.79602999721608,
            "scoreConfidence" : [
                7658.825044643276,
                7820.417104637709
            ],
            "scorePercentiles" : {
                "0.0" : 7374.135248397251,
                "50.0" : 7773.118405292593,
                "90.0" : 7813.285548616629,
                "95.0" : 7818.971273044065,
                "99.0" : 7819.416148830916,
                "99.9" : 7819.416148830916,
                "99.99" : 7819.416148830916,
                "99.999" : 7819.416148830916,
                "99.9999" : 7819.416148830916,
                "100.0" : 7819.416148830916
            },
            "scoreUnit" : "ops/s",
            "rawData" : [
                [
                    7772.148128576841,
                    7808.963328996464,
                    7773.118405292593,
                    7756.408561347219,
                    7810.187094666773,
                    7800.483547514478,
                    7764.920891862951,
                    7773.246705121787,
                    7795.322063131594,
                    7817.933229541413,
                    7774.622973406762,
                    7777.886567118999,
                    7754.39230310948,
                    7767.70951266235,
                    7790.004528148153,
                    7819.416148830916,
                    7774.563992239085,
                    7587.129609817807,
                    7374.135248397251,
                    7459.150805731962,
                    7715.053798201307,
                    7746.2576670317885,
                    7746.0830856128,
                    7744.680801089765,
                    7786.707868561723
                ]
            ]
        },
        "secondaryMetrics" : {
        }
    }
]


